cito_api/__init__.py
cito_api/client.py
cito_api-1.0.0.dist-info/licenses/LICENSE
cito_api-1.0.0.dist-info/METADATA
cito_api-1.0.0.dist-info/WHEEL
cito_api-1.0.0.dist-info/top_level.txt
cito_api-1.0.0.dist-info/RECORD
