Metadata-Version: 2.4
Name: cito-api
Version: 1.0.0
Summary: Python SDK for Cito API - Call of Duty & Fortnite Esports Data
Author-email: Cito API <support@citoapi.com>
License: MIT
Project-URL: Homepage, https://citoapi.com
Project-URL: Documentation, https://docs.citoapi.com
Project-URL: Repository, https://github.com/citoapi/cito-python
Project-URL: Issues, https://github.com/citoapi/cito-python/issues
Keywords: call of duty,cod,fortnite,esports,api,gaming,cdl,competitive gaming,statistics,players,tournaments
Classifier: Development Status :: 5 - Production/Stable
Classifier: Intended Audience :: Developers
Classifier: License :: OSI Approved :: MIT License
Classifier: Operating System :: OS Independent
Classifier: Programming Language :: Python :: 3
Classifier: Programming Language :: Python :: 3.8
Classifier: Programming Language :: Python :: 3.9
Classifier: Programming Language :: Python :: 3.10
Classifier: Programming Language :: Python :: 3.11
Classifier: Programming Language :: Python :: 3.12
Classifier: Topic :: Games/Entertainment
Classifier: Topic :: Software Development :: Libraries :: Python Modules
Requires-Python: >=3.8
License-File: LICENSE
Requires-Dist: requests>=2.25.0
Dynamic: license-file
